{"template":{"src":"file:////Users/graphicsgenerator/Desktop/20240404-gfx-worker/ae/GFX3_Templates.aepx","composition":"^Fullscreen_16x9","outputModule":"JPG","frameStart":0,"frameEnd":0,"frameIncrement":1,"outputExt":"jpg"},"assets":[{"type":"data","layerName":"^Chroma","property":"Opacity","value":"0"},{"type":"data","layerName":"^Line One*","property":"Source Text","value":"YTHX Attendance"},{"type":"data","layerName":"^Line Two","property":"Source Text","value":"Total - 2,499\nUC - 199"}],"actions":{"postrender":[{"module":"@nexrender/action-copy","input":"result_00000.jpg","output":"/Volumes/HQFS/GFX/generator/renders/GFX3_Fullscreen_16x9_9185783278854.306808176327.17411acbf48a76e6ba19a1a551c58de7/GFX3_1.jpg"}]}}