{"template":{"src":"file:////Users/graphicsgenerator/Desktop/20240404-gfx-worker/ae/GFX4_Templates.aepx","composition":"^Fullscreen_16x9","outputModule":"JPG","frameStart":0,"frameEnd":0,"frameIncrement":1,"outputExt":"jpg"},"assets":[{"type":"data","layerName":"^Chroma","property":"Opacity","value":"0"},{"type":"data","layerName":"^Line One*","property":"Source Text","value":"Ke'Ambrea Atkinson"},{"type":"data","layerName":"^Line Two","property":"Source Text","value":"Worship leader"}],"actions":{"postrender":[{"module":"@nexrender/action-copy","input":"result_00000.jpg","output":"/Volumes/HQFS/GFX/generator/renders/GFX4_Fullscreen_16x9_9329107282546.306808176327.09ba4e8d7722d28567995176d0b04d6c/GFX4_1.jpg"}]}}