{"template":{"src":"file:////Users/graphicsgenerator/Desktop/20240404-gfx-worker/ae/Q1GFXPKG_Templates.aepx","composition":"^Fullscreen_16x9","outputModule":"JPG","frameStart":0,"frameEnd":0,"frameIncrement":1,"outputExt":"jpg"},"assets":[{"type":"data","layerName":"^Chroma","property":"Opacity","value":"100"},{"type":"data","layerName":"^Line One*","property":"Source Text","value":"Dylan Moore"},{"type":"data","layerName":"^Line Two","property":"Source Text","value":"Guest Experience Director"}],"actions":{"postrender":[{"module":"@nexrender/action-copy","input":"result_00000.jpg","output":"/Volumes/HQFS/GFX/generator/renders/Q1GFXPKG_Fullscreen_16x9_10909518053073.306808176327.0aeb93ea53e876799bb5d7b3dd5ba5ab/Q1GFXPKG_1.jpg"}]}}